{
  "facility_code": "25832746",
  "institution": "WARDS CORNER BEAUTY ACADEMY",
  "city": "VIRGINIA BEACH",
  "state": "VA",
  "zip": "23462",
  "country": "USA",
  "type": "For Profit",
  "cross": 445683,
  "ope": "02108801",
  "bah": 1497,
  "poe": true,
  "yr": null,
  "gibill": 4,
  "student_veteran": null,
  "student_veteran_link": null,
  "vetsuccess_name": null,
  "vetsuccess_email": null,
  "eight_keys": null,
  "correspondence": null,
  "flight": null,
  "grad_rate": 16.9,
  "grad_rate_rank": 2252,
  "default_rate": 21.3,
  "avg_stu_loan_debt": 11720,
  "avg_stu_loan_debt_rank": 1735,
  "indicator_group": 5,
  "salary": null,
  "calendar": "nontraditional",
  "tuition_in_state": 18000,
  "tuition_out_of_state": 18000,
  "online_all": false,
  "p911_tuition_fees": 36853.62,
  "p911_recipients": 3,
  "p911_yellow_ribbon": null,
  "p911_yr_recipients": null,
  "accredited": true,
  "accreditation_type": null,
  "accreditation_status": null,
  "complaints_facility_code": null,
  "complaints_main_campus_roll_up": null,
  "complaints_financial": null,
  "complaints_quality": null,
  "complaints_refund": null,
  "complaints_marketing": null,
  "complaints_accreditation": null,
  "complaints_degree_requirements": null,
  "complaints_student_loans": null,
  "complaints_grades": null,
  "complaints_credit_transfer": null,
  "complaints_jobs": null,
  "complaints_transcript": null,
  "complaints_other": null
}